src/__init__.py
src/neccak.py
src/nlg256.py
src/nlgsecp256k1.py
src/nmal.py
nmal-0.1.1.dist-info/METADATA
nmal-0.1.1.dist-info/WHEEL
nmal-0.1.1.dist-info/top_level.txt
nmal-0.1.1.dist-info/RECORD
